RayEnvWrapper/CustomRayRemoteEnv.py
RayEnvWrapper/CustomWrapperRayVecEnv.py
RayEnvWrapper/__init__.py
RayEnvWrapper-1.0.1.dist-info/LICENSE
RayEnvWrapper-1.0.1.dist-info/METADATA
RayEnvWrapper-1.0.1.dist-info/WHEEL
RayEnvWrapper-1.0.1.dist-info/top_level.txt
RayEnvWrapper-1.0.1.dist-info/RECORD
