Metadata-Version: 2.1
Name: RayEnvWrapper
Version: 1.0.1
Summary: OpenAi's gym environment wrapper to vectorize them with Ray
Home-page: https://github.com/ingambe/RayEnvWrapper
Author: Pierre Tassel
Author-email: pierre.tassel@aau.at
Classifier: Programming Language :: Python :: 3
Classifier: License :: OSI Approved :: MIT License
Classifier: Operating System :: OS Independent
Requires-Python: >=3.8
License-File: LICENSE
Requires-Dist: gym
Requires-Dist: ray
Requires-Dist: numpy
Requires-Dist: ray[rllib]
Requires-Dist: stable-baselines3
